MANIFEST.in
README.md
setup.py
django_graphos_3.egg-info/PKG-INFO
django_graphos_3.egg-info/SOURCES.txt
django_graphos_3.egg-info/dependency_links.txt
django_graphos_3.egg-info/not-zip-safe
django_graphos_3.egg-info/top_level.txt
graphos/__init__.py
graphos/exceptions.py
graphos/models.py
graphos/tests.py
graphos/utils.py
graphos/views.py
graphos/renderers/__init__.py
graphos/renderers/base.py
graphos/renderers/flot.py
graphos/renderers/gchart.py
graphos/renderers/highcharts.py
graphos/renderers/matplotlib_renderer.py
graphos/renderers/morris.py
graphos/renderers/yui.py
graphos/sources/__init__.py
graphos/sources/base.py
graphos/sources/csv_file.py
graphos/sources/model.py
graphos/sources/mongo.py
graphos/sources/simple.py
graphos/templates/graphos/flot.html
graphos/templates/graphos/highcharts.html
graphos/templates/graphos/model_template.html
graphos/templates/graphos/redis_template.html
graphos/templates/graphos/gchart/area_chart.html
graphos/templates/graphos/gchart/bar_chart.html
graphos/templates/graphos/gchart/base.html
graphos/templates/graphos/gchart/candlestick_chart.html
graphos/templates/graphos/gchart/column_chart.html
graphos/templates/graphos/gchart/line_chart.html
graphos/templates/graphos/gchart/pie_chart.html
graphos/templates/graphos/gchart/treemap_chart.html
graphos/templates/graphos/matplotlib_renderer/line_chart.html
graphos/templates/graphos/morris/chart.html
graphos/templates/graphos/morris/donut_chart.html
graphos/templates/graphos/yui/bar_chart.html
graphos/templates/graphos/yui/base.html
graphos/templates/graphos/yui/column_chart.html
graphos/templates/graphos/yui/line_chart.html
graphos/templates/graphos/yui/pie_chart.html
graphos/test_data/accounts.csv
graphos/test_data/zips.json
graphos/test_data/mongodb/mapreduce_daily__sumof__other_time_record__hours.json
graphos/test_data/mongodb/mapreduce_daily__sumof__time_record__hours.json
graphos/test_data/mongodb/mapreduce_monthly__sumof__other_time_record__hours.json
graphos/test_data/mongodb/mapreduce_monthly__sumof__time_record__hours.json
graphos/test_data/mongodb/mapreduce_weekly__sumof__other_time_record__hours.json
