Metadata-Version: 1.1
Name: django-graphos-3
Version: 1.1
Summary: Django app to provide a JS agnostic way to work with charts for Python 3+
Home-page: http://github.com/ModusVivendi/django-graphos
Author: modusvivendi
Author-email: yellolegalpad@gmail.com
License: BSD
Platform: UNKNOWN
Classifier: Development Status :: 3 - Alpha
Classifier: Environment :: Web Environment
Classifier: Intended Audience :: Developers
Classifier: License :: OSI Approved :: BSD License
Classifier: Operating System :: OS Independent
Classifier: Programming Language :: Python
Classifier: Framework :: Django
